{
  "-MbbWBsDM1Y0bXfUc6N-": {
    "id": 1,
    "name": "Kizzee",
    "sFAisle": "Goldenrod",
    "sFBay": 1,
    "sFLevel": 1,
    "wHAisle": "Khaki",
    "wHBay": 1,
    "wHLevel": 1,
    "sFStock": 112,
    "wHStock": 7165,
    "materialsUsed": "Buick",
    "favorite": false,
    "onSale": true,
    "staffPick": true,
    "image": "http://dummyimage.com/108x100.png/5fa2dd/ffffff",
    "firebaseKey": "-MbbWBsDM1Y0bXfUc6N-"
  },
  "-MbbWBsGUjYO_FhXuRVO": {
    "id": 2,
    "name": "Rose",
    "sFAisle": "Goldenrod",
    "sFBay": 2,
    "sFLevel": 2,
    "wHAisle": "Violet",
    "wHBay": 2,
    "wHLevel": 2,
    "sFStock": 7696,
    "wHStock": 6590,
    "materialsUsed": "GMC",
    "favorite": false,
    "onSale": true,
    "staffPick": true,
    "image": "http://dummyimage.com/122x100.png/5fa2dd/ffffff",
    "firebaseKey": "-MbbWBsGUjYO_FhXuRVO"
  },
  "-MbbWBsIVG_vkvHtQBu3": {
    "id": 3,
    "name": "Kerby",
    "sFAisle": "Crimson",
    "sFBay": 3,
    "sFLevel": 3,
    "wHAisle": "Yellow",
    "wHBay": 3,
    "wHLevel": 3,
    "sFStock": 424,
    "wHStock": 896,
    "materialsUsed": "Audi",
    "favorite": true,
    "onSale": false,
    "staffPick": false,
    "image": "http://dummyimage.com/232x100.png/cc0000/ffffff",
    "firebaseKey": "-MbbWBsIVG_vkvHtQBu3"
  },
  "-MbbWBsK0sVw4ZA4tisZ": {
    "id": 4,
    "name": "Weider",
    "sFAisle": "Pink",
    "sFBay": 4,
    "sFLevel": 4,
    "wHAisle": "Red",
    "wHBay": 4,
    "wHLevel": 4,
    "sFStock": 860,
    "wHStock": 9289,
    "materialsUsed": "Nissan",
    "favorite": true,
    "onSale": true,
    "staffPick": true,
    "image": "http://dummyimage.com/233x100.png/cc0000/ffffff",
    "firebaseKey": "-MbbWBsK0sVw4ZA4tisZ"
  },
  "-MbbWBsNfZHwrMbzjZUA": {
    "id": 5,
    "name": "Trixi",
    "sFAisle": "Teal",
    "sFBay": 5,
    "sFLevel": 5,
    "wHAisle": "Puce",
    "wHBay": 5,
    "wHLevel": 5,
    "sFStock": 5922,
    "wHStock": 3622,
    "materialsUsed": "Audi",
    "favorite": false,
    "onSale": true,
    "staffPick": false,
    "image": "http://dummyimage.com/248x100.png/ff4444/ffffff",
    "firebaseKey": "-MbbWBsNfZHwrMbzjZUA"
  },
  "-MbbWBsP81E9uvQwVdBG": {
    "id": 6,
    "name": "Berna",
    "sFAisle": "Aquamarine",
    "sFBay": 6,
    "sFLevel": 6,
    "wHAisle": "Teal",
    "wHBay": 6,
    "wHLevel": 6,
    "sFStock": 791,
    "wHStock": 4021,
    "materialsUsed": "Dodge",
    "favorite": false,
    "onSale": true,
    "staffPick": true,
    "image": "http://dummyimage.com/209x100.png/ff4444/ffffff",
    "firebaseKey": "-MbbWBsP81E9uvQwVdBG"
  },
  "-MbbWBsRLitH7vhu1UTB": {
    "id": 7,
    "name": "Verile",
    "sFAisle": "Orange",
    "sFBay": 7,
    "sFLevel": 7,
    "wHAisle": "Purple",
    "wHBay": 7,
    "wHLevel": 7,
    "sFStock": 8928,
    "wHStock": 4142,
    "materialsUsed": "Morgan",
    "favorite": false,
    "onSale": true,
    "staffPick": true,
    "image": "http://dummyimage.com/236x100.png/cc0000/ffffff",
    "firebaseKey": "-MbbWBsRLitH7vhu1UTB"
  },
  "-MbbWBsTBT4LIjVa1SHd": {
    "id": 8,
    "name": "Valentia",
    "sFAisle": "Red",
    "sFBay": 8,
    "sFLevel": 8,
    "wHAisle": "Aquamarine",
    "wHBay": 8,
    "wHLevel": 8,
    "sFStock": 482,
    "wHStock": 7049,
    "materialsUsed": "Honda",
    "favorite": false,
    "onSale": true,
    "staffPick": false,
    "image": "http://dummyimage.com/193x100.png/dddddd/000000",
    "firebaseKey": "-MbbWBsTBT4LIjVa1SHd"
  },
  "-MbbWBsVINSOQcHBOZUf": {
    "id": 9,
    "name": "Reggy",
    "sFAisle": "Turquoise",
    "sFBay": 9,
    "sFLevel": 9,
    "wHAisle": "Turquoise",
    "wHBay": 9,
    "wHLevel": 9,
    "sFStock": 921,
    "wHStock": 967,
    "materialsUsed": "BMW",
    "favorite": false,
    "onSale": false,
    "staffPick": true,
    "image": "http://dummyimage.com/223x100.png/5fa2dd/ffffff",
    "firebaseKey": "-MbbWBsVINSOQcHBOZUf"
  },
  "-MbbWBsYyjxYoPmJNmnK": {
    "id": 10,
    "name": "Lin",
    "sFAisle": "Teal",
    "sFBay": 10,
    "sFLevel": 10,
    "wHAisle": "Indigo",
    "wHBay": 10,
    "wHLevel": 10,
    "sFStock": 6085,
    "wHStock": 8534,
    "materialsUsed": "Nissan",
    "favorite": true,
    "onSale": false,
    "staffPick": false,
    "image": "http://dummyimage.com/172x100.png/dddddd/000000",
    "firebaseKey": "-MbbWBsYyjxYoPmJNmnK"
  },
  "-MbbWBsbkBbzmFzCCUY8": {
    "id": 11,
    "name": "Maressa",
    "sFAisle": "Pink",
    "sFBay": 11,
    "sFLevel": 11,
    "wHAisle": "Goldenrod",
    "wHBay": 11,
    "wHLevel": 11,
    "sFStock": 4558,
    "wHStock": 8495,
    "materialsUsed": "Land Rover",
    "favorite": true,
    "onSale": false,
    "staffPick": false,
    "image": "http://dummyimage.com/157x100.png/5fa2dd/ffffff",
    "firebaseKey": "-MbbWBsbkBbzmFzCCUY8"
  },
  "-MbbWBsd_LTRMW9fq9JE": {
    "id": 12,
    "name": "Nil",
    "sFAisle": "Maroon",
    "sFBay": 12,
    "sFLevel": 12,
    "wHAisle": "Indigo",
    "wHBay": 12,
    "wHLevel": 12,
    "sFStock": 6381,
    "wHStock": 9041,
    "materialsUsed": "Lamborghini",
    "favorite": false,
    "onSale": false,
    "staffPick": false,
    "image": "http://dummyimage.com/193x100.png/cc0000/ffffff",
    "firebaseKey": "-MbbWBsd_LTRMW9fq9JE"
  },
  "-MbbWBsfo8szB9vy7k83": {
    "id": 13,
    "name": "Aime",
    "sFAisle": "Aquamarine",
    "sFBay": 13,
    "sFLevel": 13,
    "wHAisle": "Maroon",
    "wHBay": 13,
    "wHLevel": 13,
    "sFStock": 514,
    "wHStock": 1627,
    "materialsUsed": "Honda",
    "favorite": false,
    "onSale": true,
    "staffPick": false,
    "image": "http://dummyimage.com/100x100.png/ff4444/ffffff",
    "firebaseKey": "-MbbWBsfo8szB9vy7k83"
  },
  "-MbbWBshhFGtCmu5At-o": {
    "id": 14,
    "name": "Gawain",
    "sFAisle": "Blue",
    "sFBay": 14,
    "sFLevel": 14,
    "wHAisle": "Orange",
    "wHBay": 14,
    "wHLevel": 14,
    "sFStock": 4136,
    "wHStock": 4842,
    "materialsUsed": "Subaru",
    "favorite": false,
    "onSale": true,
    "staffPick": true,
    "image": "http://dummyimage.com/219x100.png/cc0000/ffffff",
    "firebaseKey": "-MbbWBshhFGtCmu5At-o"
  },
  "-MbbWBsjHQdEymCSdFV6": {
    "id": 15,
    "name": "Maia",
    "sFAisle": "Red",
    "sFBay": 15,
    "sFLevel": 15,
    "wHAisle": "Pink",
    "wHBay": 15,
    "wHLevel": 15,
    "sFStock": 8385,
    "wHStock": 9623,
    "materialsUsed": "Hyundai",
    "favorite": true,
    "onSale": false,
    "staffPick": true,
    "image": "http://dummyimage.com/229x100.png/cc0000/ffffff",
    "firebaseKey": "-MbbWBsjHQdEymCSdFV6"
  },
  "-MbbWBsmOxTbIBWPLjtW": {
    "id": 16,
    "name": "Karlotta",
    "sFAisle": "Red",
    "sFBay": 16,
    "sFLevel": 16,
    "wHAisle": "Purple",
    "wHBay": 16,
    "wHLevel": 16,
    "sFStock": 6236,
    "wHStock": 6342,
    "materialsUsed": "GMC",
    "favorite": true,
    "onSale": false,
    "staffPick": false,
    "image": "http://dummyimage.com/217x100.png/cc0000/ffffff",
    "firebaseKey": "-MbbWBsmOxTbIBWPLjtW"
  },
  "-MbbWBsoSdbF5jMun8aV": {
    "id": 17,
    "name": "Sondra",
    "sFAisle": "Yellow",
    "sFBay": 17,
    "sFLevel": 17,
    "wHAisle": "Green",
    "wHBay": 17,
    "wHLevel": 17,
    "sFStock": 3931,
    "wHStock": 9272,
    "materialsUsed": "Pontiac",
    "favorite": true,
    "onSale": false,
    "staffPick": false,
    "image": "http://dummyimage.com/241x100.png/cc0000/ffffff",
    "firebaseKey": "-MbbWBsoSdbF5jMun8aV"
  },
  "-MbbWBsqTtdSghCGEeOQ": {
    "id": 18,
    "name": "Judie",
    "sFAisle": "Aquamarine",
    "sFBay": 18,
    "sFLevel": 18,
    "wHAisle": "Khaki",
    "wHBay": 18,
    "wHLevel": 18,
    "sFStock": 3263,
    "wHStock": 103,
    "materialsUsed": "Ford",
    "favorite": true,
    "onSale": true,
    "staffPick": true,
    "image": "http://dummyimage.com/114x100.png/ff4444/ffffff",
    "firebaseKey": "-MbbWBsqTtdSghCGEeOQ"
  },
  "-MbbWBssk2oqx3Z3mKow": {
    "id": 19,
    "name": "Osborn",
    "sFAisle": "Puce",
    "sFBay": 19,
    "sFLevel": 19,
    "wHAisle": "Aquamarine",
    "wHBay": 19,
    "wHLevel": 19,
    "sFStock": 4103,
    "wHStock": 3899,
    "materialsUsed": "GMC",
    "favorite": true,
    "onSale": false,
    "staffPick": false,
    "image": "http://dummyimage.com/248x100.png/dddddd/000000",
    "firebaseKey": "-MbbWBssk2oqx3Z3mKow"
  },
  "-MbbWBsu656eRkvX6iYD": {
    "id": 20,
    "name": "Debbi",
    "sFAisle": "Maroon",
    "sFBay": 20,
    "sFLevel": 20,
    "wHAisle": "Orange",
    "wHBay": 20,
    "wHLevel": 20,
    "sFStock": 4948,
    "wHStock": 757,
    "materialsUsed": "Maserati",
    "favorite": true,
    "onSale": true,
    "staffPick": true,
    "image": "http://dummyimage.com/125x100.png/ff4444/ffffff",
    "firebaseKey": "-MbbWBsu656eRkvX6iYD"
  },
  "-MbbWBswcYARjqX8PpjF": {
    "id": 21,
    "name": "Candra",
    "sFAisle": "Goldenrod",
    "sFBay": 21,
    "sFLevel": 21,
    "wHAisle": "Yellow",
    "wHBay": 21,
    "wHLevel": 21,
    "sFStock": 5661,
    "wHStock": 1858,
    "materialsUsed": "Pontiac",
    "favorite": true,
    "onSale": false,
    "staffPick": true,
    "image": "http://dummyimage.com/162x100.png/cc0000/ffffff",
    "firebaseKey": "-MbbWBswcYARjqX8PpjF"
  },
  "-MbbWBsyUbpLaEKR8XC8": {
    "id": 22,
    "name": "Turner",
    "sFAisle": "Green",
    "sFBay": 22,
    "sFLevel": 22,
    "wHAisle": "Crimson",
    "wHBay": 22,
    "wHLevel": 22,
    "sFStock": 9164,
    "wHStock": 5053,
    "materialsUsed": "Hummer",
    "favorite": true,
    "onSale": true,
    "staffPick": true,
    "image": "http://dummyimage.com/244x100.png/cc0000/ffffff",
    "firebaseKey": "-MbbWBsyUbpLaEKR8XC8"
  },
  "-MbbWBt-oLHMkckuCr_k": {
    "id": 23,
    "name": "Robbyn",
    "sFAisle": "Teal",
    "sFBay": 23,
    "sFLevel": 23,
    "wHAisle": "Turquoise",
    "wHBay": 23,
    "wHLevel": 23,
    "sFStock": 328,
    "wHStock": 6148,
    "materialsUsed": "Mitsubishi",
    "favorite": false,
    "onSale": false,
    "staffPick": true,
    "image": "http://dummyimage.com/126x100.png/ff4444/ffffff",
    "firebaseKey": "-MbbWBt-oLHMkckuCr_k"
  },
  "-MbbWBt1Kv8L4GK2sqr1": {
    "id": 24,
    "name": "Shelia",
    "sFAisle": "Turquoise",
    "sFBay": 24,
    "sFLevel": 24,
    "wHAisle": "Mauv",
    "wHBay": 24,
    "wHLevel": 24,
    "sFStock": 1942,
    "wHStock": 817,
    "materialsUsed": "Maserati",
    "favorite": false,
    "onSale": true,
    "staffPick": false,
    "image": "http://dummyimage.com/240x100.png/cc0000/ffffff",
    "firebaseKey": "-MbbWBt1Kv8L4GK2sqr1"
  },
  "-MbbWBt3fCuELqMJNpdB": {
    "id": 25,
    "name": "Heriberto",
    "sFAisle": "Green",
    "sFBay": 25,
    "sFLevel": 25,
    "wHAisle": "Aquamarine",
    "wHBay": 25,
    "wHLevel": 25,
    "sFStock": 979,
    "wHStock": 4847,
    "materialsUsed": "Volkswagen",
    "favorite": false,
    "onSale": true,
    "staffPick": true,
    "image": "http://dummyimage.com/119x100.png/cc0000/ffffff",
    "firebaseKey": "-MbbWBt3fCuELqMJNpdB"
  }
}
